d2/__init__.py
d2/connection.py
d2/diagram.py
d2/helpers.py
d2/main.py
d2/py.typed
d2/shape.py
d2/sql_table.py
d2/style.py
d2_python-1.0.0.dist-info/WHEEL
d2_python-1.0.0.dist-info/entry_points.txt
d2_python-1.0.0.dist-info/METADATA
d2_python-1.0.0.dist-info/RECORD
