Metadata-Version: 2.3
Name: d2-python
Version: 1.0.0
Summary: An unofficial, fully typed python interface for building .d2 graph files in python.
Keywords: d2-python,d2,py-d2,d2-lang,d2-python,declarative-diagrams,diagram-language,terrastruct
Author: David Revay, Robby
Author-email: David Revay <daverevay@gmail.com>, Robby <h0rv@users.noreply.github.com>
License: MIT
Classifier: Development Status :: 5 - Production/Stable
Classifier: Intended Audience :: Developers
Classifier: License :: OSI Approved :: MIT License
Classifier: Programming Language :: Python :: 3
Classifier: Programming Language :: Python :: 3.8
Classifier: Programming Language :: Python :: 3.9
Classifier: Programming Language :: Python :: 3.10
Classifier: Programming Language :: Python :: 3.11
Classifier: Programming Language :: Python :: 3.12
Classifier: Programming Language :: Python :: 3.13
Requires-Dist: coverage>=6.5.0 ; extra == 'coverage'
Requires-Dist: pytest-cov>=4.0.0 ; extra == 'coverage'
Requires-Dist: ruff>=0.12.3 ; extra == 'dev'
Requires-Dist: mypy>=0.982 ; extra == 'dev'
Requires-Dist: pre-commit>=2.20.0 ; extra == 'dev'
Requires-Dist: pytest>=7.1.3 ; extra == 'test'
Requires-Python: >=3.8
Project-URL: Bug Tracker, https://github.com/h0rv/d2-python/issues
Project-URL: Documentation, https://github.com/h0rv/d2-python/blob/main/README.md
Project-URL: Repository, https://github.com/h0rv/d2-python
Provides-Extra: coverage
Provides-Extra: dev
Provides-Extra: test
